sshmenu/__init__.py
sshmenu/__main__.py
sshmenu/sshmenu.py
sshmenu-0.0.4.dist-info/DESCRIPTION.rst
sshmenu-0.0.4.dist-info/METADATA
sshmenu-0.0.4.dist-info/RECORD
sshmenu-0.0.4.dist-info/WHEEL
sshmenu-0.0.4.dist-info/entry_points.txt
sshmenu-0.0.4.dist-info/metadata.json
sshmenu-0.0.4.dist-info/top_level.txt
