Metadata-Version: 2.0
Name: sshmenu
Version: 0.0.4
Summary: Command line SSH menu and helper utility
Home-page: https://github.com/mmeyer724/sshmenu
Author: Michael Meyer
Author-email: michael@meyer.io
License: MIT
Platform: UNKNOWN
Classifier: Environment :: Console
Classifier: Intended Audience :: Developers
Classifier: Natural Language :: English
Classifier: License :: OSI Approved :: MIT License
Classifier: Programming Language :: Python :: 3
Requires-Dist: args (==0.1.0)
Requires-Dist: clint (==0.5.1)
Requires-Dist: readchar (==0.7)
